pubsub/__init__.py
pubsub/protocol.py
pubsub/adapters/__init__.py
pubsub/adapters/base.py
pubsub/adapters/exceptions.py
pubsub/adapters/googlecloud.py
pubsub/adapters/http.py
pubsub/filters/__init__.py
pubsub/filters/filter.py
pubsub/serializers/__init__.py
pubsub/serializers/serializer.py
pubsub/validators/__init__.py
pubsub/validators/resolver.py
pubsub/validators/validator.py
pubsub.py-1.0.0.dist-info/DESCRIPTION.rst
pubsub.py-1.0.0.dist-info/LICENSE.txt
pubsub.py-1.0.0.dist-info/METADATA
pubsub.py-1.0.0.dist-info/RECORD
pubsub.py-1.0.0.dist-info/WHEEL
pubsub.py-1.0.0.dist-info/metadata.json
pubsub.py-1.0.0.dist-info/top_level.txt
tests/__init__.py
tests/test_protocols.py
tests/test_validators.py
