Metadata-Version: 2.0
Name: pubsub.py
Version: 1.0.0
Summary: Python PubSub Adapter for gcloud
Home-page: https://github.com/Superbalist/python-pubsub
Author: Superbalist Engineering
Author-email: tech@superbalist.com
License: UNKNOWN
Platform: UNKNOWN
Requires-Dist: google.cloud.pubsub (==0.33.1)
Requires-Dist: jsonschema
Requires-Dist: requests
